rmpy/NpVaR.py
rmpy/PaVaR.py
rmpy/__init__.py
rmpy/inputs_handler.py
rmpy-1.2.4.dist-info/METADATA
rmpy-1.2.4.dist-info/WHEEL
rmpy-1.2.4.dist-info/top_level.txt
rmpy-1.2.4.dist-info/RECORD
