Metadata-Version: 2.1
Name: rmpy
Version: 1.2.4
Summary: This Python package provides a comprehensive set of tools for calculating and analyzing Non-Parametric and Parametric Value-at-Risk (NpVaR and pVaR).
Home-page: https://github.com/GianMarcoOddo/rmpy
Author: Gian Marco Oddo, Mattia Aprea, Sofia Compagnoni
Author-email: gian.marco.oddo@usi.ch, mattia.aprea@usi.ch, sofia.compagnoni@usi.ch
License: MIT
Requires-Dist: numpy
Requires-Dist: pandas
Requires-Dist: yfinance
Requires-Dist: scipy
